grid_feedback_optimizer/__init__.py
grid_feedback_optimizer/main.py
grid_feedback_optimizer/engine/__init__.py
grid_feedback_optimizer/engine/grad_proj_optimizer.py
grid_feedback_optimizer/engine/powerflow.py
grid_feedback_optimizer/engine/primal_dual_optimizer.py
grid_feedback_optimizer/engine/renew_gen_projection.py
grid_feedback_optimizer/engine/solve.py
grid_feedback_optimizer/models/__init__.py
grid_feedback_optimizer/models/loader.py
grid_feedback_optimizer/models/network.py
grid_feedback_optimizer/models/solve_data.py
grid_feedback_optimizer/utils/__init__.py
grid_feedback_optimizer/utils/utils.py
grid_feedback_optimizer-0.1.13.dist-info/licenses/LICENSE
grid_feedback_optimizer-0.1.13.dist-info/METADATA
grid_feedback_optimizer-0.1.13.dist-info/WHEEL
grid_feedback_optimizer-0.1.13.dist-info/top_level.txt
grid_feedback_optimizer-0.1.13.dist-info/RECORD
