Metadata-Version: 2.4
Name: grid_feedback_optimizer
Version: 0.1.13
Summary: Optimization methods for voltage and congestion management in modern power distribution grids.
Author-email: Sen Zhan <sen.zhan@outlook.com>
License: MIT
Project-URL: Homepage, https://github.com/senzhanopt/grid_feedback_optimizer
Project-URL: Repository, https://github.com/senzhanopt/grid_feedback_optimizer
Requires-Python: >=3.12
License-File: LICENSE
Requires-Dist: cvxpy>=1.7.3
Requires-Dist: matplotlib>=3.10.7
Requires-Dist: numpy>=2.3.4
Requires-Dist: openpyxl>=3.1.5
Requires-Dist: pandas>=2.3.3
Requires-Dist: power-grid-model>=1.12.60
Requires-Dist: pydantic>=2.12.3
Provides-Extra: dev
Requires-Dist: black>=25.9.0; extra == "dev"
Requires-Dist: ipykernel>=7.1.0; extra == "dev"
Requires-Dist: isort>=7.0.0; extra == "dev"
Requires-Dist: pylint>=4.0.2; extra == "dev"
Requires-Dist: pytest>=8.4.2; extra == "dev"
Requires-Dist: sphinx>=8.2.3; extra == "dev"
Requires-Dist: sphinx-rtd-theme>=3.0.2; extra == "dev"
Dynamic: license-file
